gftools/__init__.py
gftools/_version.py
gftools/argparse.py
gftools/article.py
gftools/axes.proto
gftools/axes_pb2.py
gftools/constants.py
gftools/designers.proto
gftools/designers_pb2.py
gftools/fix.py
gftools/fonts_public.proto
gftools/fonts_public_pb2.py
gftools/gfgithub.py
gftools/instancer.py
gftools/knowledge.proto
gftools/knowledge_pb2.py
gftools/logging.py
gftools/qa.py
gftools/stat.py
gftools/subsetmerger.py
gftools/template.upstream.yaml
gftools/udhr_all.txt
gftools/ufomerge.py
gftools/utils.py
gftools/builder/__init__.py
gftools/builder/__main__.py
gftools/builder/autohint.py
gftools/builder/build_vtt.py
gftools/builder/dependencies.py
gftools/builder/file.py
gftools/builder/fontc.py
gftools/builder/schema.py
gftools/builder/jobrunner/__init__.py
gftools/builder/jobrunner/__main__.py
gftools/builder/operations/__init__.py
gftools/builder/operations/addChws.py
gftools/builder/operations/addSpacingAxis.py
gftools/builder/operations/addSubset.py
gftools/builder/operations/autohint.py
gftools/builder/operations/autohintOTF.py
gftools/builder/operations/buildAvar2.py
gftools/builder/operations/buildFvarInstances.py
gftools/builder/operations/buildOTF.py
gftools/builder/operations/buildStat.py
gftools/builder/operations/buildTTF.py
gftools/builder/operations/buildVTT.py
gftools/builder/operations/buildVariable.py
gftools/builder/operations/compress.py
gftools/builder/operations/copy.py
gftools/builder/operations/exec.py
gftools/builder/operations/featureFreeze.py
gftools/builder/operations/fix.py
gftools/builder/operations/fontsetter.py
gftools/builder/operations/glyphs2ds.py
gftools/builder/operations/hbsubset.py
gftools/builder/operations/instantiateUfo.py
gftools/builder/operations/paintcompiler.py
gftools/builder/operations/remap.py
gftools/builder/operations/remapLayout.py
gftools/builder/operations/rename.py
gftools/builder/operations/subspace.py
gftools/builder/operations/fontc/__init__.py
gftools/builder/operations/fontc/fontcBuildOTF.py
gftools-0.9.99.dist-info/licenses/LICENSE
gftools-0.9.99.dist-info/METADATA
gftools-0.9.99.dist-info/WHEEL
gftools-0.9.99.dist-info/entry_points.txt
gftools-0.9.99.dist-info/top_level.txt
gftools-0.9.99.dist-info/RECORD
