Metadata-Version: 2.4
Name: gftools
Version: 0.9.99
Summary: Google Fonts Tools is a set of command-line tools for testing font projects
Author: Felipe Sanches, Lasse Fister, Eli Heuer, Roderick Sheeter
Author-email: Marc Foley <m.foley.88@gmail.com>, Dave Crossland <dave@lab6.com>, Simon Cozens <simon@simon-cozens.org>
Classifier: Environment :: Console
Classifier: Intended Audience :: Developers
Classifier: Topic :: Text Processing :: Fonts
Classifier: License :: OSI Approved :: Apache Software License
Classifier: Operating System :: OS Independent
Classifier: Programming Language :: Python :: 3
Classifier: Programming Language :: Python :: 3.10
Classifier: Programming Language :: Python :: 3.11
Classifier: Programming Language :: Python :: 3.12
Classifier: Programming Language :: Python :: 3.13
Classifier: Programming Language :: Python :: 3.14
Requires-Python: >=3.10
License-File: LICENSE
Requires-Dist: FontTools[ufo]>=4.60.0
Requires-Dist: axisregistry>=0.4.9
Requires-Dist: absl-py
Requires-Dist: glyphsLib
Requires-Dist: gflanguages>=0.6.0
Requires-Dist: gfsubsets>=2024.02.05
Requires-Dist: glyphsets>=0.6.13
Requires-Dist: PyGithub
Requires-Dist: pillow
Requires-Dist: protobuf<4,>=3.19.4
Requires-Dist: requests
Requires-Dist: tabulate
Requires-Dist: unidecode
Requires-Dist: opentype-sanitizer
Requires-Dist: vttlib
Requires-Dist: pygit2>=1.16.0
Requires-Dist: strictyaml
Requires-Dist: fontmake[json]>=3.3.0
Requires-Dist: skia-pathops
Requires-Dist: statmake
Requires-Dist: PyYAML
Requires-Dist: babelfont
Requires-Dist: ttfautohint-py
Requires-Dist: brotli
Requires-Dist: jinja2
Requires-Dist: fontFeatures
Requires-Dist: vharfbuzz
Requires-Dist: bumpfontversion
Requires-Dist: nanoemoji>=0.15.0
Requires-Dist: font-v
Requires-Dist: afdko
Requires-Dist: beautifulsoup4
Requires-Dist: rich
Requires-Dist: packaging
Requires-Dist: ninja
Requires-Dist: networkx
Requires-Dist: ruamel.yaml
Requires-Dist: ffmpeg-python
Requires-Dist: ufomerge>=1.8.1
Requires-Dist: tomli; python_version < "3.11"
Provides-Extra: qa
Requires-Dist: fontbakery[googlefonts]; extra == "qa"
Requires-Dist: diffenator2>=0.2.0; extra == "qa"
Requires-Dist: pycairo; extra == "qa"
Provides-Extra: test
Requires-Dist: black==24.10.0; extra == "test"
Requires-Dist: pytest; extra == "test"
Dynamic: license-file
